daixm_env/__init__.py
daixm_env/backends.py
daixm_env/base.py
daixm_env/utils.py
daixm_env-1.0.0.dist-info/METADATA
daixm_env-1.0.0.dist-info/WHEEL
daixm_env-1.0.0.dist-info/entry_points.txt
daixm_env-1.0.0.dist-info/top_level.txt
daixm_env-1.0.0.dist-info/RECORD
