Metadata-Version: 2.1
Name: daixm-env
Version: 1.0.0
Summary: UNKNOWN
Home-page: UNKNOWN
Author: 
Author-email: 
License: UNKNOWN
Platform: UNKNOWN
Requires-Dist: envparse (==0.2.0)
Requires-Dist: simplejson (>=3.10.0)
Requires-Dist: six (>=1.11.0)
Requires-Dist: pyapollo (>=0.0.9)
Requires-Dist: M2Crypto (>=0.28.0)
Requires-Dist: pytest (<5.0.0)
Provides-Extra: testing
Requires-Dist: pytest ; extra == 'testing'
